Project 2/Full Adder/FA.v
module FullAdder(a,b,cin,sum,cout);

    input a,b,cin;
    output sum, cout;

    assign sum = (((a & ~b) | (~a & b)) & ~ cin) | (~((a & ~b) | (~a & b)) & cin);
    assign ccout = (((a & b) | (a & cin)) | (b & cin));

endmodule

Project 2/Full Adder/FA_tb.v
`timescale 1ns/1ns
`include "FA.v"

module FullAdder_tb;

    reg a,b,cin;
    wire sum, cout;

    FullAdder uut(a,b,cin,sum,cout);

    initial begin

        $dumpfile("FA_tb.vcd");
        $dumpvars(0, FullAdder_tb);

        {a,b,cin} = 3'b000; #20;
        {a,b,cin} = 3'b001; #20;
        {a,b,cin} = 3'b010; #20;
        {a,b,cin} = 3'b011; #20;
        {a,b,cin} = 3'b100; #20;
        {a,b,cin} = 3'b101; #20;
        {a,b,cin} = 3'b110; #20;
        {a,b,cin} = 3'b111; #20;

        $display("Test Complete");

    end

endmodule

Project 2/Full Adder/FA_tb.vcd
$date
	Mon Oct  6 16:31:29 2025
$end
$version
	Icarus Verilog
$end
$timescale
	1ns
$end
$scope module FullAdder_tb $end
$var wire 1 ! cout $end
$var wire 1 " sum $end
$var reg 1 # a $end
$var reg 1 $ b $end
$var reg 1 % cin $end
$scope module uut $end
$var wire 1 # a $end
$var wire 1 $ b $end
$var wire 1 & ccout $end
$var wire 1 % cin $end
$var wire 1 ! cout $end
$var wire 1 " sum $end
$upscope $end
$upscope $end
$enddefinitions $end
$comment Show the parameter values. $end
$dumpall
$end
#0
$dumpvars
0&
0%
0$
0#
0"
z!
$end
#20
1"
1%
#40
1"
1$
0%
#60
0"
1&
1%
#80
1"
0&
1#
0$
0%
#100
0"
1&
1%
#120
0"
1$
0%
#140
1"
1%
