Project 2/Full Adder/FA.v
module FullAdder(a,b,c,sum,carry);

    input a,b,c;
    output sum, carry;

    assign sum = (((a & ~b) | (~a & b)) & ~ c) | (~((a & ~b) | (~a & b)) & c);
    assign carry = (((a & b) | (a & c)) | (b & c));

endmodule

Project 2/Full Adder/FA_tb.v
`timescale 1ns/1ns
`include "FA.v"

module FullAdder_tb;

    reg a,b,c;
    wire sum, carry;

    FullAdder uut(a,b,c,sum,carry);

    initial begin

        $dumpfile("FA_tb.vcd");
        $dumpvars(0, FullAdder_tb);

        {a,b,c} = 3'b000; #20;
        {a,b,c} = 3'b001; #20;
        {a,b,c} = 3'b010; #20;
        {a,b,c} = 3'b011; #20;
        {a,b,c} = 3'b100; #20;
        {a,b,c} = 3'b101; #20;
        {a,b,c} = 3'b110; #20;
        {a,b,c} = 3'b111; #20;

        $display("Test Complete");

    end

endmodule

Project 2/Full Adder/FA_tb.vcd
$date
	Thu Oct  2 17:52:51 2025
$end
$version
	Icarus Verilog
$end
$timescale
	1ns
$end
$scope module FullAdder_tb $end
$var wire 1 ! sum $end
$var wire 1 " carry $end
$var reg 1 # a $end
$var reg 1 $ b $end
$var reg 1 % c $end
$scope module uut $end
$var wire 1 # a $end
$var wire 1 $ b $end
$var wire 1 % c $end
$var wire 1 " carry $end
$var wire 1 ! sum $end
$upscope $end
$upscope $end
$enddefinitions $end
$comment Show the parameter values. $end
$dumpall
$end
#0
$dumpvars
0%
0$
0#
0"
0!
$end
#20
1!
1%
#40
1!
1$
0%
#60
0!
1"
1%
#80
1!
0"
1#
0$
0%
#100
0!
1"
1%
#120
0!
1$
0%
#140
1!
1%
