Project 1/Mux/Mux.v
module Mux(a,b,sel,out);

input a,b,sel;
output out;

assign out = (a*~sel)| (b*sel);

endmodule

Project 1/Mux/Mux_tb.v
`timescale 1ns/1ns
`include "Mux.v"

module Mux_tb();

    reg a,b,sel;
    wire out;

    Mux uut(a,b,sel,out);

    initial begin

        $dumpfile("Mux_tb.vcd");
        $dumpvars(0, Mux_tb);

        {a,b,sel} = 3'b000; #20;
        {a,b,sel} = 3'b010; #20;
        {a,b,sel} = 3'b100; #20;
        {a,b,sel} = 3'b110; #20;
        {a,b,sel} = 3'b001; #20;
        {a,b,sel} = 3'b011; #20;
        {a,b,sel} = 3'b101; #20;
        {a,b,sel} = 3'b111; #20;
        $display("Test Complete");

    end

endmodule

Project 1/Mux/Mux_tb.vcd
$date
	Wed Sep 24 22:25:20 2025
$end
$version
	Icarus Verilog
$end
$timescale
	1ns
$end
$scope module Mux_tb $end
$var wire 1 ! out $end
$var reg 1 " a $end
$var reg 1 # b $end
$var reg 1 $ sel $end
$scope module uut $end
$var wire 1 " a $end
$var wire 1 # b $end
$var wire 1 ! out $end
$var wire 1 $ sel $end
$upscope $end
$upscope $end
$enddefinitions $end
$comment Show the parameter values. $end
$dumpall
$end
#0
$dumpvars
0$
0#
0"
0!
$end
#20
1#
#40
1!
1"
0#
#60
1#
#80
0!
0"
0#
1$
#100
1!
1#
#120
0!
1"
0#
#140
1!
1#
