Project 1/Mux4Way16/Mux4Way16.v
module Mux4Way16(a,b,c,d,sel,out);

    input [15:0] a,b,c,d;
    input [1:0] sel;
    output [15:0] out;

    assign out = sel[1] ? (sel[0] ? d : c) : (sel[0] ? b : a);
    //assign out = (sel[1] & ~((a & ~sel[0]) | (b & sel[0]))) | (sel[1] & (c & ~sel[0]) | (d & sel[0]));
    /*assign out =    (~sel[1] * ~sel[0] * a) + 
                    (~sel[1] * sel[0] * b) +
                    (sel[1] * ~sel[0] * c) +
                    (sel[1] * sel[0] * d);*/

endmodule

Project 1/Mux4Way16/Mux4Way16_tb.v
`timescale 1ns/1ns
`include "Mux4Way16.v"

module Mux4Way16_tb;

reg [15:0] a,b,c,d;
reg [1:0] sel;
output [15:0] out;

Mux4Way16 uut(a,b,c,d,sel,out);

initial begin

    $dumpfile("Mux4Way16_tb.vcd");
    $dumpvars(0, Mux4Way16_tb);


    {a,b,c,d} = 4'b0000; sel = 00; #20; sel = 01; #20; sel = 10; #20; sel = 11; #20;
    {a,b,c,d} = 64'b0001001000110100100110000111011010101010101010100101010101010101;
    sel = 00; #20; sel = 01; #20; sel = 10; #20; sel = 11; #20;

    $display("test Complete");

end


endmodule;

Project 1/Mux4Way16/Mux4Way16_tb.vcd
$date
	Thu Oct  2 16:14:44 2025
$end
$version
	Icarus Verilog
$end
$timescale
	1ns
$end
$scope module Mux4Way16_tb $end
$var wire 16 ! out [15:0] $end
$var reg 16 " a [15:0] $end
$var reg 16 # b [15:0] $end
$var reg 16 $ c [15:0] $end
$var reg 16 % d [15:0] $end
$var reg 2 & sel [1:0] $end
$scope module uut $end
$var wire 16 ' a [15:0] $end
$var wire 16 ( b [15:0] $end
$var wire 16 ) c [15:0] $end
$var wire 16 * d [15:0] $end
$var wire 2 + sel [1:0] $end
$var wire 16 , out [15:0] $end
$upscope $end
$upscope $end
$enddefinitions $end
$comment Show the parameter values. $end
$dumpall
$end
#0
$dumpvars
b0 ,
b0 +
b0 *
b0 )
b0 (
b0 '
b0 &
b0 %
b0 $
b0 #
b0 "
b0 !
$end
#20
b1 &
b1 +
#40
b10 &
b10 +
#60
b11 &
b11 +
#80
b1001000110100 !
b1001000110100 ,
b0 &
b0 +
b1001000110100 "
b1001000110100 '
b1001100001110110 #
b1001100001110110 (
b1010101010101010 $
b1010101010101010 )
b101010101010101 %
b101010101010101 *
#100
b1001100001110110 !
b1001100001110110 ,
b1 &
b1 +
#120
b1010101010101010 !
b1010101010101010 ,
b10 &
b10 +
#140
b101010101010101 !
b101010101010101 ,
b11 &
b11 +
